textode/__init__.py
textode/constants.py
textode/nodes.py
textode/register.py
textode-2.0.0.dist-info/LICENSE
textode-2.0.0.dist-info/METADATA
textode-2.0.0.dist-info/WHEEL
textode-2.0.0.dist-info/top_level.txt
textode-2.0.0.dist-info/RECORD
