Metadata-Version: 2.1
Name: textode
Version: 2.0.0
Summary: Make your text-bot with only one handler.
Home-page: https://github.com/Masynchin/textode
Author-email: masynchin@gmail.com
License: MIT
Platform: UNKNOWN
Requires-Python: >=3.7
License-File: LICENSE
